<?xml version="1.0" encoding="UTF-8"?>
<Index xmlns="http://www.tso.co.uk/assets/namespace/gazetteindex" editionCode="L" page="028" pageID="https://www.thegazette.co.uk/id/London/index/year/1994/volume/1/page/028" pagePDF="https://www.thegazette.co.uk/London/index/year/1994/volume/1/page/028" pageRDF="https://www.thegazette.co.uk/London/index/year/1994/volume/1/page/028?view=linked-data" type="index" volume="1" year="1994">
  <ItemGroup>
    <MainItem>
      <Key>Reynolds</Key>
      <Forenames>P. B. M</Forenames>
      <PageNumber>3993</PageNumber>
    </MainItem>
  </ItemGroup>
  <ItemGroup>
    <MainItem>
      <Key>Reynolds</Key>
      <Forenames>S. K. P.</Forenames>
      <PageNumber>20689</PageNumber>
    </MainItem>
  </ItemGroup>
  <ItemGroup>
    <MainItem>
      <Key>Rhodes</Key>
      <Forenames>A. J</Forenames>
      <PageNumber>1520</PageNumber>
    </MainItem>
  </ItemGroup>
  <ItemGroup>
    <MainItem>
      <Key>Rhodes</Key>
      <Forenames>K. P</Forenames>
      <PageNumber>3999</PageNumber>
    </MainItem>
  </ItemGroup>
  <ItemGroup>
    <MainItem>
      <Key>Rice</Key>
      <Forenames>J. A</Forenames>
      <PageNumber>2318</PageNumber>
    </MainItem>
  </ItemGroup>
  <ItemGroup>
    <MainItem>
      <Key>Rich</Key>
      <Forenames>A. H</Forenames>
      <PageNumber>3174</PageNumber>
    </MainItem>
  </ItemGroup>
  <ItemGroup>
    <MainItem>
      <Key>Richards</Key>
      <Forenames>A. D</Forenames>
      <PageNumber>1515</PageNumber>
    </MainItem>
  </ItemGroup>
  <ItemGroup>
    <MainItem>
      <Key>Richards</Key>
      <Forenames>D</Forenames>
      <PageNumber>3999</PageNumber>
    </MainItem>
  </ItemGroup>
  <ItemGroup>
    <MainItem>
      <Key>Richards</Key>
      <Forenames>E</Forenames>
      <PageNumber>4781</PageNumber>
    </MainItem>
  </ItemGroup>
  <ItemGroup>
    <MainItem>
      <Key>Richards</Key>
      <Forenames>G. B</Forenames>
      <PageNumber>2315</PageNumber>
    </MainItem>
  </ItemGroup>
  <ItemGroup>
    <MainItem>
      <Key>Richards</Key>
      <Forenames>N. W. F</Forenames>
      <PageNumber>3172</PageNumber>
    </MainItem>
  </ItemGroup>
  <ItemGroup>
    <MainItem>
      <Key>Richards</Key>
      <Forenames>P. J</Forenames>
      <PageNumber>2754</PageNumber>
    </MainItem>
  </ItemGroup>
  <ItemGroup>
    <MainItem>
      <Key>Richards</Key>
      <Forenames>P. R</Forenames>
      <PageNumber>2318</PageNumber>
    </MainItem>
  </ItemGroup>
  <ItemGroup>
    <MainItem>
      <Key>Richardson</Key>
      <Forenames>A. D.</Forenames>
      <PageNumber>20689</PageNumber>
    </MainItem>
  </ItemGroup>
  <ItemGroup>
    <MainItem>
      <Key>Richardson</Key>
      <Forenames>J</Forenames>
      <PageNumber>20679</PageNumber>
    </MainItem>
  </ItemGroup>
  <ItemGroup>
    <MainItem>
      <Key>Richardson</Key>
      <Forenames>J. D</Forenames>
      <PageNumber>3994</PageNumber>
    </MainItem>
  </ItemGroup>
  <ItemGroup>
    <MainItem>
      <Key>Richardson</Key>
      <Forenames>K</Forenames>
      <PageNumber>20690</PageNumber>
    </MainItem>
  </ItemGroup>
  <ItemGroup>
    <MainItem>
      <Key>Richardson</Key>
      <Forenames>M. H</Forenames>
      <PageNumber>3181</PageNumber>
    </MainItem>
  </ItemGroup>
  <ItemGroup>
    <MainItem>
      <Key>Richardson</Key>
      <Forenames>M. P</Forenames>
      <PageNumber>3174</PageNumber>
    </MainItem>
  </ItemGroup>
  <ItemGroup>
    <MainItem>
      <Key>Richardson</Key>
      <Forenames>P. J</Forenames>
      <PageNumber>3993</PageNumber>
    </MainItem>
  </ItemGroup>
  <ItemGroup>
    <MainItem>
      <Key>Riches</Key>
      <Forenames>S. M</Forenames>
      <PageNumber>1092</PageNumber>
    </MainItem>
  </ItemGroup>
  <ItemGroup>
    <MainItem>
      <Key>Richmond</Key>
      <Forenames>J. K</Forenames>
      <PageNumber>4385</PageNumber>
    </MainItem>
  </ItemGroup>
  <ItemGroup>
    <MainItem>
      <Key>Richter</Key>
      <Forenames>A. G</Forenames>
      <PageNumber>20684</PageNumber>
    </MainItem>
  </ItemGroup>
  <ItemGroup>
    <MainItem>
      <Key>Rickards</Key>
      <Forenames>T. J</Forenames>
      <PageNumber>4000</PageNumber>
    </MainItem>
  </ItemGroup>
  <ItemGroup>
    <MainItem>
      <Key>Riddell</Key>
      <Forenames>G</Forenames>
      <PageNumber>20689</PageNumber>
    </MainItem>
  </ItemGroup>
  <ItemGroup>
    <MainItem>
      <Key>Riddick</Key>
      <Forenames>D. W. G</Forenames>
      <PageNumber>3994</PageNumber>
    </MainItem>
  </ItemGroup>
  <ItemGroup>
    <MainItem>
      <Key>Ridgway</Key>
      <Forenames>A. P</Forenames>
      <PageNumber>20680</PageNumber>
    </MainItem>
  </ItemGroup>
  <ItemGroup>
    <MainItem>
      <Key>Rigby</Key>
      <Forenames>J. D</Forenames>
      <PageNumber>2320</PageNumber>
    </MainItem>
  </ItemGroup>
  <ItemGroup>
    <MainItem>
      <Key>Rigby</Key>
      <Forenames>M. P</Forenames>
      <PageNumber>1918</PageNumber>
    </MainItem>
  </ItemGroup>
  <ItemGroup>
    <MainItem>
      <Key>Riley</Key>
      <Forenames>A. J</Forenames>
      <PageNumber>2321</PageNumber>
    </MainItem>
  </ItemGroup>
  <ItemGroup>
    <MainItem>
      <Key>Riley</Key>
      <Forenames>K. J</Forenames>
      <PageNumber>1089</PageNumber>
    </MainItem>
  </ItemGroup>
  <ItemGroup>
    <MainItem>
      <Key>Riley</Key>
      <Forenames>M. J</Forenames>
      <PageNumber>1515</PageNumber>
    </MainItem>
  </ItemGroup>
  <ItemGroup>
    <MainItem>
      <Key>Riley</Key>
      <Forenames>M. T</Forenames>
      <PageNumber>3176</PageNumber>
    </MainItem>
  </ItemGroup>
  <ItemGroup>
    <MainItem>
      <Key>Ripley</Key>
      <Forenames>D. J</Forenames>
      <PageNumber>1087</PageNumber>
    </MainItem>
  </ItemGroup>
  <ItemGroup>
    <MainItem>
      <Key>Rishman</Key>
      <Forenames>G</Forenames>
      <PageNumber>4785</PageNumber>
    </MainItem>
  </ItemGroup>
  <ItemGroup>
    <MainItem>
      <Key>Ritchie</Key>
      <Forenames>A.J</Forenames>
      <PageNumber>2320</PageNumber>
    </MainItem>
  </ItemGroup>
  <ItemGroup>
    <MainItem>
      <Key>Ritchie</Key>
      <Forenames>L</Forenames>
      <PageNumber>3997</PageNumber>
      <PageNumber>20685</PageNumber>
    </MainItem>
  </ItemGroup>
  <ItemGroup>
    <MainItem>
      <Key>Robbins</Key>
      <Forenames>J. E</Forenames>
      <PageNumber>3999</PageNumber>
    </MainItem>
  </ItemGroup>
  <ItemGroup>
    <MainItem>
      <Key>Robbins</Key>
      <Forenames>J. M. F</Forenames>
      <PageNumber>1516</PageNumber>
    </MainItem>
  </ItemGroup>
  <ItemGroup>
    <MainItem>
      <Key>Roberson</Key>
      <Forenames>S. C</Forenames>
      <PageNumber>4000</PageNumber>
    </MainItem>
  </ItemGroup>
  <ItemGroup>
    <MainItem>
      <Key>Roberts</Key>
      <Forenames>B. C</Forenames>
      <PageNumber>1922</PageNumber>
    </MainItem>
  </ItemGroup>
  <ItemGroup>
    <MainItem>
      <Key>Roberts</Key>
      <Forenames>C. A</Forenames>
      <PageNumber>1520</PageNumber>
    </MainItem>
  </ItemGroup>
  <ItemGroup>
    <MainItem>
      <Key>Roberts</Key>
      <Forenames>C. J</Forenames>
      <PageNumber>1090</PageNumber>
    </MainItem>
  </ItemGroup>
  <ItemGroup>
    <MainItem>
      <Key>Roberts</Key>
      <Forenames>D. P. M</Forenames>
      <PageNumber>20687</PageNumber>
    </MainItem>
  </ItemGroup>
  <ItemGroup>
    <MainItem>
      <Key>Roberts</Key>
      <Forenames>G. P</Forenames>
      <PageNumber>1088</PageNumber>
    </MainItem>
  </ItemGroup>
  <ItemGroup>
    <MainItem>
      <Key>Roberts</Key>
      <Forenames>J. D</Forenames>
      <PageNumber>20690</PageNumber>
    </MainItem>
  </ItemGroup>
  <ItemGroup>
    <MainItem>
      <Key>Roberts</Key>
      <Forenames>M. J</Forenames>
      <PageNumber>1521</PageNumber>
    </MainItem>
  </ItemGroup>
  <ItemGroup>
    <MainItem>
      <Key>Roberts</Key>
      <Forenames>P. A</Forenames>
      <PageNumber>4779</PageNumber>
    </MainItem>
  </ItemGroup>
  <ItemGroup>
    <MainItem>
      <Key>Roberts</Key>
      <Forenames>P. E</Forenames>
      <PageNumber>20684</PageNumber>
    </MainItem>
  </ItemGroup>
  <ItemGroup>
    <MainItem>
      <Key>Roberts</Key>
      <Forenames>P. W. F</Forenames>
      <PageNumber>1520</PageNumber>
    </MainItem>
  </ItemGroup>
  <ItemGroup>
    <MainItem>
      <Key>Roberts</Key>
      <Forenames>R</Forenames>
      <PageNumber>1524</PageNumber>
    </MainItem>
  </ItemGroup>
  <ItemGroup>
    <MainItem>
      <Key>Roberts</Key>
      <Forenames>V. M</Forenames>
      <PageNumber>1917</PageNumber>
    </MainItem>
  </ItemGroup>
  <ItemGroup>
    <MainItem>
      <Key>Robertson</Key>
      <Forenames>A. R</Forenames>
      <PageNumber>2322</PageNumber>
    </MainItem>
  </ItemGroup>
  <ItemGroup>
    <MainItem>
      <Key>Robertson</Key>
      <Forenames>C. S. A.</Forenames>
      <PageNumber>1094</PageNumber>
    </MainItem>
  </ItemGroup>
  <ItemGroup>
    <MainItem>
      <Key>Robertson</Key>
      <Forenames>D. B</Forenames>
      <PageNumber>20683</PageNumber>
    </MainItem>
  </ItemGroup>
  <ItemGroup>
    <MainItem>
      <Key>Robertson</Key>
      <Forenames>D. S.</Forenames>
      <PageNumber>1518</PageNumber>
      <PageNumber>4780</PageNumber>
    </MainItem>
  </ItemGroup>
  <ItemGroup>
    <MainItem>
      <Key>Robertson</Key>
      <Forenames>F. K</Forenames>
      <PageNumber>2317</PageNumber>
    </MainItem>
  </ItemGroup>
  <ItemGroup>
    <MainItem>
      <Key>Robertson</Key>
      <Forenames>I. G</Forenames>
      <PageNumber>3178</PageNumber>
    </MainItem>
  </ItemGroup>
  <ItemGroup>
    <MainItem>
      <Key>Robertson</Key>
      <Forenames>K. R</Forenames>
      <PageNumber>3991</PageNumber>
    </MainItem>
  </ItemGroup>
  <ItemGroup>
    <MainItem>
      <Key>Robertson</Key>
      <Forenames>L. M</Forenames>
      <PageNumber>1089</PageNumber>
    </MainItem>
  </ItemGroup>
  <ItemGroup>
    <MainItem>
      <Key>Robertson</Key>
      <Forenames>R. A. D.</Forenames>
      <PageNumber>20689</PageNumber>
    </MainItem>
  </ItemGroup>
  <ItemGroup>
    <MainItem>
      <Key>Robertson</Key>
      <Forenames>S. D</Forenames>
      <PageNumber>1921</PageNumber>
    </MainItem>
  </ItemGroup>
  <ItemGroup>
    <MainItem>
      <Key>Robertson</Key>
      <Forenames>S. G</Forenames>
      <PageNumber>1090</PageNumber>
    </MainItem>
  </ItemGroup>
  <ItemGroup>
    <MainItem>
      <Key>Robertson-Steel</Key>
      <Forenames>L. E.</Forenames>
      <PageNumber>2753</PageNumber>
    </MainItem>
  </ItemGroup>
  <ItemGroup>
    <MainItem>
      <Key>Robins</Key>
      <Forenames>A. C. R</Forenames>
      <PageNumber>1094</PageNumber>
    </MainItem>
  </ItemGroup>
  <ItemGroup>
    <MainItem>
      <Key>Robins</Key>
      <Forenames>P. R</Forenames>
      <PageNumber>4785</PageNumber>
    </MainItem>
  </ItemGroup>
  <ItemGroup>
    <MainItem>
      <Key>Robinson</Key>
      <Forenames>C</Forenames>
      <PageNumber>1520</PageNumber>
    </MainItem>
  </ItemGroup>
  <ItemGroup>
    <MainItem>
      <Key>Robinson</Key>
      <Forenames>C. A</Forenames>
      <PageNumber>20685</PageNumber>
    </MainItem>
  </ItemGroup>
  <ItemGroup>
    <MainItem>
      <Key>Robinson</Key>
      <Forenames>C. E</Forenames>
      <PageNumber>1920</PageNumber>
    </MainItem>
  </ItemGroup>
  <ItemGroup>
    <MainItem>
      <Key>Robinson</Key>
      <Forenames>D. A</Forenames>
      <PageNumber>20687</PageNumber>
    </MainItem>
  </ItemGroup>
  <ItemGroup>
    <MainItem>
      <Key>Robinson</Key>
      <Forenames>J. C</Forenames>
      <PageNumber>3179</PageNumber>
    </MainItem>
  </ItemGroup>
  <ItemGroup>
    <MainItem>
      <Key>Robinson</Key>
      <Forenames>J. K</Forenames>
      <PageNumber>4001</PageNumber>
    </MainItem>
  </ItemGroup>
  <ItemGroup>
    <MainItem>
      <Key>Robinson</Key>
      <Forenames>J. R</Forenames>
      <PageNumber>3991</PageNumber>
    </MainItem>
  </ItemGroup>
  <ItemGroup>
    <MainItem>
      <Key>Robinson</Key>
      <Forenames>K. L</Forenames>
      <PageNumber>3179</PageNumber>
    </MainItem>
  </ItemGroup>
  <ItemGroup>
    <MainItem>
      <Key>Robinson</Key>
      <Forenames>N. J</Forenames>
      <PageNumber>1088</PageNumber>
    </MainItem>
  </ItemGroup>
  <ItemGroup>
    <MainItem>
      <Key>Robinson</Key>
      <Forenames>R. J</Forenames>
      <PageNumber>2754</PageNumber>
    </MainItem>
  </ItemGroup>
  <ItemGroup>
    <MainItem>
      <Key>Robinson</Key>
      <Forenames>R. S</Forenames>
      <PageNumber>2316</PageNumber>
    </MainItem>
  </ItemGroup>
  <ItemGroup>
    <MainItem>
      <Key>Roblin</Key>
      <Forenames>D. J. H</Forenames>
      <PageNumber>4383</PageNumber>
    </MainItem>
  </ItemGroup>
  <ItemGroup>
    <MainItem>
      <Key>Robson</Key>
      <Forenames>D. P</Forenames>
      <PageNumber>4390</PageNumber>
    </MainItem>
  </ItemGroup>
  <ItemGroup>
    <MainItem>
      <Key>Robson</Key>
      <Forenames>N. A. H</Forenames>
      <PageNumber>2320</PageNumber>
    </MainItem>
  </ItemGroup>
  <ItemGroup>
    <MainItem>
      <Key>Rodda</Key>
      <Forenames>S. G</Forenames>
      <PageNumber>20689</PageNumber>
    </MainItem>
  </ItemGroup>
  <ItemGroup>
    <MainItem>
      <Key>Roebuck</Key>
      <Forenames>G. E</Forenames>
      <PageNumber>2322</PageNumber>
    </MainItem>
  </ItemGroup>
  <ItemGroup>
    <MainItem>
      <Key>Roger</Key>
      <Forenames>G</Forenames>
      <PageNumber>3175</PageNumber>
    </MainItem>
  </ItemGroup>
  <ItemGroup>
    <MainItem>
      <Key>Rogers</Key>
      <Forenames>A. D</Forenames>
      <PageNumber>1524</PageNumber>
    </MainItem>
  </ItemGroup>
  <ItemGroup>
    <MainItem>
      <Key>Rogers</Key>
      <Forenames>A. G</Forenames>
      <PageNumber>3992</PageNumber>
    </MainItem>
  </ItemGroup>
  <ItemGroup>
    <MainItem>
      <Key>Rogers</Key>
      <Forenames>D. J. P</Forenames>
      <PageNumber>1095</PageNumber>
    </MainItem>
  </ItemGroup>
  <ItemGroup>
    <MainItem>
      <Key>Rogers</Key>
      <Forenames>G. L</Forenames>
      <PageNumber>20687</PageNumber>
    </MainItem>
  </ItemGroup>
  <ItemGroup>
    <MainItem>
      <Key>Rogers</Key>
      <Forenames>H. P</Forenames>
      <PageNumber>2317</PageNumber>
    </MainItem>
  </ItemGroup>
  <ItemGroup>
    <MainItem>
      <Key>Rogers</Key>
      <Forenames>N. C</Forenames>
      <PageNumber>20689</PageNumber>
    </MainItem>
  </ItemGroup>
  <ItemGroup>
    <MainItem>
      <Key>Rogers</Key>
      <Forenames>P. E</Forenames>
      <PageNumber>3174</PageNumber>
    </MainItem>
  </ItemGroup>
  <ItemGroup>
    <MainItem>
      <Key>Rogers</Key>
      <Forenames>S. A</Forenames>
      <PageNumber>20681</PageNumber>
    </MainItem>
  </ItemGroup>
  <ItemGroup>
    <MainItem>
      <Key>Rogers-Jones</Key>
      <Forenames>A</Forenames>
      <PageNumber>4000</PageNumber>
    </MainItem>
  </ItemGroup>
  <ItemGroup>
    <MainItem>
      <Key>Rogerson</Key>
      <Forenames>J. F</Forenames>
      <PageNumber>3173</PageNumber>
    </MainItem>
  </ItemGroup>
  <ItemGroup>
    <MainItem>
      <Key>Rolf</Key>
      <Forenames>J</Forenames>
      <PageNumber>2321</PageNumber>
    </MainItem>
  </ItemGroup>
  <ItemGroup>
    <MainItem>
      <Key>Rolfe</Key>
      <Forenames>T. J</Forenames>
      <PageNumber>2322</PageNumber>
    </MainItem>
  </ItemGroup>
  <ItemGroup>
    <MainItem>
      <Key>Ronaldson</Key>
      <Forenames>D. D</Forenames>
      <PageNumber>4001</PageNumber>
    </MainItem>
  </ItemGroup>
  <ItemGroup>
    <MainItem>
      <Key>Roney</Key>
      <Forenames>P</Forenames>
      <PageNumber>4780</PageNumber>
    </MainItem>
  </ItemGroup>
  <ItemGroup>
    <MainItem>
      <Key>Roofe</Key>
      <Forenames>J</Forenames>
      <PageNumber>2321</PageNumber>
    </MainItem>
  </ItemGroup>
  <ItemGroup>
    <MainItem>
      <Key>Rooke</Key>
      <Forenames>H. J. P. D</Forenames>
      <PageNumber>3172</PageNumber>
    </MainItem>
  </ItemGroup>
  <ItemGroup>
    <MainItem>
      <Key>Rooney</Key>
      <Forenames>W</Forenames>
      <PageNumber>1524</PageNumber>
    </MainItem>
  </ItemGroup>
  <ItemGroup>
    <MainItem>
      <Key>Rooney</Key>
      <Forenames>W. J</Forenames>
      <PageNumber>4784</PageNumber>
    </MainItem>
  </ItemGroup>
  <ItemGroup>
    <MainItem>
      <Key>Ropes</Key>
      <Forenames>J. J</Forenames>
      <PageNumber>3172</PageNumber>
    </MainItem>
  </ItemGroup>
  <ItemGroup>
    <MainItem>
      <Key>Rosborough</Key>
      <Forenames>P</Forenames>
      <PageNumber>4782</PageNumber>
    </MainItem>
  </ItemGroup>
  <ItemGroup>
    <MainItem>
      <Key>Rose</Key>
      <Forenames>A. C. C</Forenames>
      <PageNumber>20682</PageNumber>
    </MainItem>
  </ItemGroup>
  <ItemGroup>
    <MainItem>
      <Key>Rose</Key>
      <Forenames>A. J</Forenames>
      <PageNumber>3994</PageNumber>
      <PageNumber>4385</PageNumber>
    </MainItem>
  </ItemGroup>
  <ItemGroup>
    <MainItem>
      <Key>Rose</Key>
      <Forenames>L. J</Forenames>
      <PageNumber>3180</PageNumber>
    </MainItem>
  </ItemGroup>
  <ItemGroup>
    <MainItem>
      <Key>Rose</Key>
      <Forenames>M</Forenames>
      <PageNumber>1917</PageNumber>
    </MainItem>
  </ItemGroup>
  <ItemGroup>
    <MainItem>
      <Key>Rose</Key>
      <Forenames>P. W</Forenames>
      <PageNumber>1095</PageNumber>
    </MainItem>
  </ItemGroup>
  <ItemGroup>
    <MainItem>
      <Key>Roskelly</Key>
      <Forenames>J. H. E</Forenames>
      <PageNumber>3995</PageNumber>
    </MainItem>
  </ItemGroup>
  <ItemGroup>
    <MainItem>
      <Key>Ross</Key>
      <Text>AG</Text>
      <PageNumber>3172</PageNumber>
      <PageNumber>4386</PageNumber>
    </MainItem>
  </ItemGroup>
  <ItemGroup>
    <MainItem>
      <Key>Ross</Key>
      <Forenames>E. A</Forenames>
      <PageNumber>1094</PageNumber>
    </MainItem>
  </ItemGroup>
  <ItemGroup>
    <MainItem>
      <Key>Ross</Key>
      <Forenames>F. A</Forenames>
      <PageNumber>1522</PageNumber>
    </MainItem>
  </ItemGroup>
  <ItemGroup>
    <MainItem>
      <Key>Ross</Key>
      <Forenames>I. A</Forenames>
      <PageNumber>2321</PageNumber>
    </MainItem>
  </ItemGroup>
  <ItemGroup>
    <MainItem>
      <Key>Ross</Key>
      <Forenames>I. D</Forenames>
      <PageNumber>1524</PageNumber>
    </MainItem>
  </ItemGroup>
  <ItemGroup>
    <MainItem>
      <Key>Ross</Key>
      <Forenames>I. M</Forenames>
      <PageNumber>2317</PageNumber>
    </MainItem>
  </ItemGroup>
  <ItemGroup>
    <MainItem>
      <Key>Ross</Key>
      <Forenames>J. M</Forenames>
      <PageNumber>2318</PageNumber>
      <PageNumber>3997</PageNumber>
    </MainItem>
  </ItemGroup>
  <ItemGroup>
    <MainItem>
      <Key>Ross</Key>
      <Forenames>J. W</Forenames>
      <PageNumber>20689</PageNumber>
    </MainItem>
  </ItemGroup>
  <ItemGroup>
    <MainItem>
      <Key>Rothnie</Key>
      <Forenames>N. C</Forenames>
      <PageNumber>1090</PageNumber>
    </MainItem>
  </ItemGroup>
  <ItemGroup>
    <MainItem>
      <Key>Roulinson</Key>
      <Forenames>D. E</Forenames>
      <PageNumber>20687</PageNumber>
    </MainItem>
  </ItemGroup>
  <ItemGroup>
    <MainItem>
      <Key>Rous</Key>
      <Forenames>W</Forenames>
      <PageNumber>2316</PageNumber>
    </MainItem>
  </ItemGroup>
  <ItemGroup>
    <MainItem>
      <Key>Rowan</Key>
      <Forenames>J. F</Forenames>
      <PageNumber>20684</PageNumber>
    </MainItem>
  </ItemGroup>
  <ItemGroup>
    <MainItem>
      <Key>Rowe</Key>
      <Forenames>M. F</Forenames>
      <PageNumber>1518</PageNumber>
    </MainItem>
  </ItemGroup>
  <ItemGroup>
    <MainItem>
      <Key>Roy</Key>
      <Forenames>J. L. S</Forenames>
      <PageNumber>1524</PageNumber>
    </MainItem>
  </ItemGroup>
  <ItemGroup>
    <MainItem>
      <Key>Royal</Key>
      <Forenames>M. J</Forenames>
      <PageNumber>3173</PageNumber>
    </MainItem>
  </ItemGroup>
  <ItemGroup>
    <MainItem>
      <Key>Royall</Key>
      <Forenames>T. G</Forenames>
      <PageNumber>3173</PageNumber>
    </MainItem>
  </ItemGroup>
  <ItemGroup>
    <MainItem>
      <Key>Rudling-Smith</Key>
      <Forenames>R. D.</Forenames>
      <PageNumber>3996</PageNumber>
    </MainItem>
  </ItemGroup>
  <ItemGroup>
    <MainItem>
      <Key>Rudrabaheadur</Key>
      <Forenames>Gurung</Forenames>
      <PageNumber>20683</PageNumber>
    </MainItem>
  </ItemGroup>
  <ItemGroup>
    <MainItem>
      <Key>Ruglys</Key>
      <Forenames>M.P</Forenames>
      <PageNumber>20681</PageNumber>
    </MainItem>
  </ItemGroup>
  <ItemGroup>
    <MainItem>
      <Key>Runciman</Key>
      <Forenames>P. A. M. E.</Forenames>
      <PageNumber>3177</PageNumber>
    </MainItem>
  </ItemGroup>
  <ItemGroup>
    <MainItem>
      <Key>Rush</Key>
      <Forenames>M. H</Forenames>
      <PageNumber>4392</PageNumber>
    </MainItem>
  </ItemGroup>
  <ItemGroup>
    <MainItem>
      <Key>Rushton</Key>
      <Forenames>P. W</Forenames>
      <PageNumber>20683</PageNumber>
    </MainItem>
  </ItemGroup>
  <ItemGroup>
    <MainItem>
      <Key>Ruske</Key>
      <Forenames>J. W</Forenames>
      <PageNumber>20681</PageNumber>
    </MainItem>
  </ItemGroup>
  <ItemGroup>
    <MainItem>
      <Key>Russell</Key>
      <Forenames>B</Forenames>
      <PageNumber>709</PageNumber>
    </MainItem>
  </ItemGroup>
  <ItemGroup>
    <MainItem>
      <Key>Russell</Key>
      <Forenames>D. J</Forenames>
      <PageNumber>1515</PageNumber>
    </MainItem>
  </ItemGroup>
  <ItemGroup>
    <MainItem>
      <Key>Russell</Key>
      <Forenames>G. P</Forenames>
      <PageNumber>20687</PageNumber>
    </MainItem>
  </ItemGroup>
  <ItemGroup>
    <MainItem>
      <Key>Russell</Key>
      <Forenames>J. B</Forenames>
      <PageNumber>1520</PageNumber>
    </MainItem>
  </ItemGroup>
  <ItemGroup>
    <MainItem>
      <Key>Russell</Key>
      <Forenames>S</Forenames>
      <PageNumber>2320</PageNumber>
    </MainItem>
  </ItemGroup>
  <ItemGroup>
    <MainItem>
      <Key>Russell</Key>
      <Forenames>S. L</Forenames>
      <PageNumber>3996</PageNumber>
    </MainItem>
  </ItemGroup>
  <ItemGroup>
    <MainItem>
      <Key>Russell</Key>
      <Forenames>W. H.</Forenames>
      <PageNumber>3172</PageNumber>
      <PageNumber>4383</PageNumber>
    </MainItem>
  </ItemGroup>
  <ItemGroup>
    <MainItem>
      <Key>Rutherford</Key>
      <Forenames>A</Forenames>
      <PageNumber>2753</PageNumber>
    </MainItem>
  </ItemGroup>
  <ItemGroup>
    <MainItem>
      <Key>Ryan</Key>
      <Forenames>A</Forenames>
      <PageNumber>1092</PageNumber>
    </MainItem>
  </ItemGroup>
  <ItemGroup>
    <MainItem>
      <Key>Ryan</Key>
      <Forenames>P. A</Forenames>
      <PageNumber>4000</PageNumber>
    </MainItem>
  </ItemGroup>
  <ItemGroup>
    <MainItem>
      <Key>Ryder</Key>
      <Forenames>A</Forenames>
      <PageNumber>20688</PageNumber>
    </MainItem>
  </ItemGroup>
  <ItemGroup>
    <MainItem>
      <Key>Sacre</Key>
      <Forenames>J. F</Forenames>
      <PageNumber>2322</PageNumber>
    </MainItem>
  </ItemGroup>
  <ItemGroup>
    <MainItem>
      <Key>Sadler</Key>
      <Forenames>J. J</Forenames>
      <PageNumber>3171</PageNumber>
    </MainItem>
  </ItemGroup>
  <ItemGroup>
    <MainItem>
      <Key>Sage</Key>
      <Forenames>V. M. J</Forenames>
      <PageNumber>3171</PageNumber>
    </MainItem>
  </ItemGroup>
  <ItemGroup>
    <MainItem>
      <Key>Saksida</Key>
      <Forenames>K. T. D</Forenames>
      <PageNumber>3995</PageNumber>
    </MainItem>
  </ItemGroup>
  <ItemGroup>
    <MainItem>
      <Key>Sale</Key>
      <Forenames>R. A</Forenames>
      <PageNumber>20680</PageNumber>
    </MainItem>
  </ItemGroup>
  <ItemGroup>
    <MainItem>
      <Key>Sail</Key>
      <Text>1</Text>
      <PageNumber>1094</PageNumber>
    </MainItem>
  </ItemGroup>
  <ItemGroup>
    <MainItem>
      <Key>Salmon</Key>
      <Forenames>R. E</Forenames>
      <PageNumber>4000</PageNumber>
    </MainItem>
  </ItemGroup>
  <ItemGroup>
    <MainItem>
      <Key>Salmon</Key>
      <Forenames>R. E. A</Forenames>
      <PageNumber>4388</PageNumber>
    </MainItem>
  </ItemGroup>
  <ItemGroup>
    <MainItem>
      <Key>Salter</Key>
      <Forenames>A. T. J</Forenames>
      <PageNumber>4781</PageNumber>
    </MainItem>
  </ItemGroup>
  <ItemGroup>
    <MainItem>
      <Key>Salter</Key>
      <Forenames>D.J. H</Forenames>
      <PageNumber>3991</PageNumber>
    </MainItem>
  </ItemGroup>
  <ItemGroup>
    <MainItem>
      <Key>Salter</Key>
      <Forenames>R. C</Forenames>
      <PageNumber>3173</PageNumber>
    </MainItem>
  </ItemGroup>
  <ItemGroup>
    <MainItem>
      <Key>Samra</Key>
      <Forenames>G. S</Forenames>
      <PageNumber>3178</PageNumber>
    </MainItem>
  </ItemGroup>
  <ItemGroup>
    <MainItem>
      <Key>Sanderson</Key>
      <Forenames>D</Forenames>
      <PageNumber>1093</PageNumber>
    </MainItem>
  </ItemGroup>
  <ItemGroup>
    <MainItem>
      <Key>Sanderson</Key>
      <Forenames>D. P</Forenames>
      <PageNumber>2752</PageNumber>
    </MainItem>
  </ItemGroup>
  <ItemGroup>
    <MainItem>
      <Key>Sanderson</Key>
      <Forenames>J. S</Forenames>
      <PageNumber>20691</PageNumber>
    </MainItem>
  </ItemGroup>
  <ItemGroup>
    <MainItem>
      <Key>Sanderson</Key>
      <Forenames>K. S</Forenames>
      <PageNumber>3173</PageNumber>
    </MainItem>
  </ItemGroup>
  <ItemGroup>
    <MainItem>
      <Key>Sandford</Key>
      <Forenames>R. J</Forenames>
      <PageNumber>709</PageNumber>
    </MainItem>
  </ItemGroup>
  <ItemGroup>
    <MainItem>
      <Key>Sands</Key>
      <Forenames>M. T</Forenames>
      <PageNumber>3996</PageNumber>
    </MainItem>
  </ItemGroup>
  <ItemGroup>
    <MainItem>
      <Key>Sapwell</Key>
      <Forenames>C.</Forenames>
      <Text>i</Text>
      <PageNumber>2319</PageNumber>
    </MainItem>
  </ItemGroup>
  <ItemGroup>
    <MainItem>
      <Key>Sargent</Key>
      <Forenames>R. T</Forenames>
      <PageNumber>3992</PageNumber>
    </MainItem>
  </ItemGroup>
  <ItemGroup>
    <MainItem>
      <Key>Sarkar</Key>
      <Forenames>P. K</Forenames>
      <PageNumber>1919</PageNumber>
    </MainItem>
  </ItemGroup>
  <ItemGroup>
    <MainItem>
      <Key>Sauberlich</Key>
      <Forenames>P. W. G.</Forenames>
      <PageNumber>4780</PageNumber>
    </MainItem>
  </ItemGroup>
  <ItemGroup>
    <MainItem>
      <Key>Saul</Key>
      <Forenames>G. C</Forenames>
      <PageNumber>20685</PageNumber>
    </MainItem>
  </ItemGroup>
  <ItemGroup>
    <MainItem>
      <Key>Saunders</Key>
      <Forenames>G</Forenames>
      <Text>-</Text>
      <PageNumber>3174</PageNumber>
    </MainItem>
  </ItemGroup>
  <ItemGroup>
    <MainItem>
      <Key>Saunders</Key>
      <Forenames>R. J</Forenames>
      <PageNumber>2320</PageNumber>
    </MainItem>
  </ItemGroup>
  <ItemGroup>
    <MainItem>
      <Key>Savage</Key>
      <Forenames>A</Forenames>
      <PageNumber>3181</PageNumber>
    </MainItem>
  </ItemGroup>
  <ItemGroup>
    <MainItem>
      <Key>Savage</Key>
      <Forenames>F. E. J</Forenames>
      <PageNumber>1919</PageNumber>
    </MainItem>
  </ItemGroup>
  <ItemGroup>
    <MainItem>
      <Key>Sawers</Key>
      <Forenames>I. J</Forenames>
      <PageNumber>3176</PageNumber>
    </MainItem>
  </ItemGroup>
  <ItemGroup>
    <MainItem>
      <Key>Sawyer</Key>
      <Forenames>W. M</Forenames>
      <PageNumber>711</PageNumber>
    </MainItem>
  </ItemGroup>
  <ItemGroup>
    <MainItem>
      <Key>Sayer</Key>
      <Forenames>C. J</Forenames>
      <PageNumber>20681</PageNumber>
    </MainItem>
  </ItemGroup>
  <ItemGroup>
    <MainItem>
      <Key>Sayer</Key>
      <Forenames>M. H. W</Forenames>
      <PageNumber>3998</PageNumber>
    </MainItem>
  </ItemGroup>
  <ItemGroup>
    <MainItem>
      <Key>Scade</Key>
      <Forenames>T. P</Forenames>
      <PageNumber>1521</PageNumber>
    </MainItem>
  </ItemGroup>
  <ItemGroup>
    <MainItem>
      <Key>Scales</Key>
      <Forenames>J. A</Forenames>
      <PageNumber>20685</PageNumber>
    </MainItem>
  </ItemGroup>
  <ItemGroup>
    <MainItem>
      <Key>Scandling</Key>
      <Forenames>P</Forenames>
      <PageNumber>3991</PageNumber>
    </MainItem>
  </ItemGroup>
  <ItemGroup>
    <MainItem>
      <Key>Scarratt</Key>
      <Forenames>W. A</Forenames>
      <PageNumber>2749</PageNumber>
    </MainItem>
  </ItemGroup>
  <ItemGroup>
    <MainItem>
      <Key>Schmalenbach</Key>
      <Text>MR</Text>
      <PageNumber>4784</PageNumber>
    </MainItem>
  </ItemGroup>
  <ItemGroup>
    <MainItem>
      <Key>Schofield</Key>
      <Forenames>S. B</Forenames>
      <PageNumber>20690</PageNumber>
    </MainItem>
  </ItemGroup>
  <ItemGroup>
    <MainItem>
      <Key>Schroder</Key>
      <Forenames>J</Forenames>
      <PageNumber>711</PageNumber>
    </MainItem>
  </ItemGroup>
  <ItemGroup>
    <MainItem>
      <Key>Scott</Key>
      <Forenames>C. A. R</Forenames>
      <PageNumber>2751</PageNumber>
    </MainItem>
  </ItemGroup>
  <ItemGroup>
    <MainItem>
      <Key>Scott</Key>
      <Forenames>C. M. G</Forenames>
      <PageNumber>20682</PageNumber>
    </MainItem>
  </ItemGroup>
  <ItemGroup>
    <MainItem>
      <Key>Scott</Key>
      <Forenames>F. G</Forenames>
      <PageNumber>20688</PageNumber>
    </MainItem>
  </ItemGroup>
  <ItemGroup>
    <MainItem>
      <Key>Scott</Key>
      <Forenames>M. D</Forenames>
      <PageNumber>1094</PageNumber>
    </MainItem>
  </ItemGroup>
  <ItemGroup>
    <MainItem>
      <Key>Scott</Key>
      <Forenames>M. M</Forenames>
      <PageNumber>1516</PageNumber>
    </MainItem>
  </ItemGroup>
  <ItemGroup>
    <MainItem>
      <Key>Scott</Key>
      <Forenames>R</Forenames>
      <PageNumber>3180</PageNumber>
    </MainItem>
  </ItemGroup>
  <ItemGroup>
    <MainItem>
      <Key>Scott</Key>
      <Forenames>R. A. H</Forenames>
      <PageNumber>4784</PageNumber>
    </MainItem>
  </ItemGroup>
  <ItemGroup>
    <MainItem>
      <Key>Scott</Key>
      <Forenames>R. S</Forenames>
      <PageNumber>1524</PageNumber>
    </MainItem>
  </ItemGroup>
  <ItemGroup>
    <MainItem>
      <Key>Scott</Key>
      <Forenames>W. D</Forenames>
      <PageNumber>2317</PageNumber>
    </MainItem>
  </ItemGroup>
  <ItemGroup>
    <MainItem>
      <Key>Scott-Lewis</Key>
      <Forenames>I. R</Forenames>
      <PageNumber>3994</PageNumber>
    </MainItem>
  </ItemGroup>
  <ItemGroup>
    <MainItem>
      <Key>Scroggs</Key>
      <Forenames>L. M</Forenames>
      <PageNumber>1921</PageNumber>
    </MainItem>
  </ItemGroup>
  <ItemGroup>
    <MainItem>
      <Key>Seal</Key>
      <Forenames>A. J</Forenames>
      <PageNumber>20684</PageNumber>
    </MainItem>
  </ItemGroup>
  <ItemGroup>
    <MainItem>
      <Key>Seal</Key>
      <Forenames>D</Forenames>
      <PageNumber>709</PageNumber>
    </MainItem>
  </ItemGroup>
  <ItemGroup>
    <MainItem>
      <Key>Searight</Key>
      <Forenames>S. R. C</Forenames>
      <PageNumber>3173</PageNumber>
    </MainItem>
  </ItemGroup>
  <ItemGroup>
    <MainItem>
      <Key>Searl</Key>
      <Forenames>P. D</Forenames>
      <PageNumber>3999</PageNumber>
    </MainItem>
  </ItemGroup>
  <ItemGroup>
    <MainItem>
      <Key>Searle</Key>
      <Forenames>J. P</Forenames>
      <PageNumber>2751</PageNumber>
    </MainItem>
  </ItemGroup>
  <ItemGroup>
    <MainItem>
      <Key>Searle</Key>
      <Forenames>N. A</Forenames>
      <PageNumber>20683</PageNumber>
    </MainItem>
  </ItemGroup>
  <ItemGroup>
    <MainItem>
      <Key>Seaton</Key>
      <Forenames>I. G</Forenames>
      <PageNumber>1524</PageNumber>
    </MainItem>
  </ItemGroup>
  <ItemGroup>
    <MainItem>
      <Key>Seivwright</Key>
      <Forenames>A. M</Forenames>
      <PageNumber>1918</PageNumber>
    </MainItem>
  </ItemGroup>
  <ItemGroup>
    <MainItem>
      <Key>Selby</Key>
      <Forenames>N. P. R</Forenames>
      <PageNumber>2748</PageNumber>
    </MainItem>
  </ItemGroup>
  <ItemGroup>
    <MainItem>
      <Key>Selby</Key>
      <Forenames>R. L</Forenames>
      <PageNumber>4392</PageNumber>
    </MainItem>
  </ItemGroup>
  <ItemGroup>
    <MainItem>
      <Key>Sellwood</Key>
      <Forenames>R. J</Forenames>
      <PageNumber>1518</PageNumber>
    </MainItem>
  </ItemGroup>
  <ItemGroup>
    <MainItem>
      <Key>Selmes</Key>
      <Forenames>D. A</Forenames>
      <PageNumber>4780</PageNumber>
    </MainItem>
  </ItemGroup>
  <ItemGroup>
    <MainItem>
      <Key>Semple</Key>
      <Forenames>R. A</Forenames>
      <PageNumber>1518</PageNumber>
    </MainItem>
  </ItemGroup>
  <ItemGroup>
    <MainItem>
      <Key>Senior</Key>
      <Forenames>J. W</Forenames>
      <PageNumber>1519</PageNumber>
    </MainItem>
  </ItemGroup>
  <ItemGroup>
    <MainItem>
      <Key>Sergeant</Key>
      <Forenames>P. S</Forenames>
      <PageNumber>3181</PageNumber>
    </MainItem>
  </ItemGroup>
  <ItemGroup>
    <MainItem>
      <Key>Seward</Key>
      <Text>CM</Text>
      <PageNumber>3999</PageNumber>
    </MainItem>
  </ItemGroup>
  <ItemGroup>
    <MainItem>
      <Key>Seward</Key>
      <Forenames>R. H. P</Forenames>
      <PageNumber>4780</PageNumber>
    </MainItem>
  </ItemGroup>
  <ItemGroup>
    <MainItem>
      <Key>Sewell</Key>
      <Forenames>D. N. W</Forenames>
      <PageNumber>3175</PageNumber>
    </MainItem>
  </ItemGroup>
  <ItemGroup>
    <MainItem>
      <Key>Sewell</Key>
      <Forenames>R. G</Forenames>
      <PageNumber>2754</PageNumber>
    </MainItem>
  </ItemGroup>
  <ItemGroup>
    <MainItem>
      <Key>Sexton</Key>
      <Forenames>G</Forenames>
      <PageNumber>20690</PageNumber>
    </MainItem>
  </ItemGroup>
  <ItemGroup>
    <MainItem>
      <Key>Sexton</Key>
      <Forenames>M. S</Forenames>
      <PageNumber>2321</PageNumber>
    </MainItem>
  </ItemGroup>
  <ItemGroup>
    <MainItem>
      <Key>Seymour</Key>
      <Forenames>A. C. P</Forenames>
      <PageNumber>338</PageNumber>
    </MainItem>
  </ItemGroup>
  <ItemGroup>
    <MainItem>
      <Key>Seymour-Dale</Key>
      <Forenames>S. A</Forenames>
      <PageNumber>337</PageNumber>
    </MainItem>
  </ItemGroup>
  <ItemGroup>
    <MainItem>
      <Key>Shackleton</Key>
      <Forenames>R. C. E.</Forenames>
      <PageNumber>3173</PageNumber>
    </MainItem>
  </ItemGroup>
  <ItemGroup>
    <MainItem>
      <Key>Shadbolt</Key>
      <Forenames>S. E</Forenames>
      <PageNumber>1516</PageNumber>
    </MainItem>
  </ItemGroup>
  <ItemGroup>
    <MainItem>
      <Key>Shakespere</Key>
      <Forenames>P. H</Forenames>
      <PageNumber>3992</PageNumber>
    </MainItem>
  </ItemGroup>
  <ItemGroup>
    <MainItem>
      <Key>Shamsher</Key>
      <Forenames>Gurune</Forenames>
      <PageNumber>1089</PageNumber>
    </MainItem>
  </ItemGroup>
  <ItemGroup>
    <MainItem>
      <Key>Shannon</Key>
      <Forenames>C. K</Forenames>
      <PageNumber>20684</PageNumber>
    </MainItem>
  </ItemGroup>
  <ItemGroup>
    <MainItem>
      <Key>Sharkey</Key>
      <Forenames>A. J</Forenames>
      <PageNumber>1918</PageNumber>
    </MainItem>
  </ItemGroup>
  <ItemGroup>
    <MainItem>
      <Key>Sharland</Key>
      <Forenames>R. E</Forenames>
      <PageNumber>2320</PageNumber>
    </MainItem>
  </ItemGroup>
  <ItemGroup>
    <MainItem>
      <Key>Sharman</Key>
      <Forenames>D. A</Forenames>
      <PageNumber>1517</PageNumber>
    </MainItem>
  </ItemGroup>
  <ItemGroup>
    <MainItem>
      <Key>Sharp</Key>
      <Forenames>C</Forenames>
      <PageNumber>2320</PageNumber>
    </MainItem>
  </ItemGroup>
  <ItemGroup>
    <MainItem>
      <Key>Shatford</Key>
      <Forenames>W. F</Forenames>
      <PageNumber>4000</PageNumber>
    </MainItem>
  </ItemGroup>
  <ItemGroup>
    <MainItem>
      <Key>Shaw</Key>
      <Forenames>A. D. P</Forenames>
      <PageNumber>4384</PageNumber>
    </MainItem>
  </ItemGroup>
  <ItemGroup>
    <MainItem>
      <Key>Shaw</Key>
      <Forenames>D. M</Forenames>
      <PageNumber>20689</PageNumber>
    </MainItem>
  </ItemGroup>
  <ItemGroup>
    <MainItem>
      <Key>Shaw</Key>
      <Forenames>G. B</Forenames>
      <PageNumber>1519</PageNumber>
    </MainItem>
  </ItemGroup>
  <ItemGroup>
    <MainItem>
      <Key>Shaw</Key>
      <Forenames>J</Forenames>
      <PageNumber>3172</PageNumber>
    </MainItem>
  </ItemGroup>
  <ItemGroup>
    <MainItem>
      <Key>Shea</Key>
      <Forenames>K. Y</Forenames>
      <PageNumber>3180</PageNumber>
    </MainItem>
  </ItemGroup>
  <ItemGroup>
    <MainItem>
      <Key>Sheldon</Key>
      <Forenames>D. M</Forenames>
      <PageNumber>712</PageNumber>
    </MainItem>
  </ItemGroup>
  <ItemGroup>
    <MainItem>
      <Key>Sheldon</Key>
      <Forenames>J. J. K</Forenames>
      <PageNumber>4780</PageNumber>
    </MainItem>
  </ItemGroup>
  <ItemGroup>
    <MainItem>
      <Key>Sheldon</Key>
      <Forenames>R. J</Forenames>
      <PageNumber>3174</PageNumber>
    </MainItem>
  </ItemGroup>
  <ItemGroup>
    <MainItem>
      <Key>Shelley</Key>
      <Forenames>K. D</Forenames>
      <PageNumber>1094</PageNumber>
    </MainItem>
  </ItemGroup>
  <ItemGroup>
    <MainItem>
      <Key>Shephard</Key>
      <Forenames>P. C</Forenames>
      <PageNumber>3996</PageNumber>
    </MainItem>
  </ItemGroup>
  <ItemGroup>
    <MainItem>
      <Key>Shepherd</Key>
      <Forenames>M. P</Forenames>
      <PageNumber>3991</PageNumber>
    </MainItem>
  </ItemGroup>
  <ItemGroup>
    <MainItem>
      <Key>Shepherd</Key>
      <Forenames>R. F. D</Forenames>
      <PageNumber>4384</PageNumber>
    </MainItem>
  </ItemGroup>
  <ItemGroup>
    <MainItem>
      <Key>Sheppard</Key>
      <Forenames>K. J</Forenames>
      <PageNumber>4783</PageNumber>
    </MainItem>
  </ItemGroup>
  <ItemGroup>
    <MainItem>
      <Key>Sheppard</Key>
      <Forenames>N. A</Forenames>
      <PageNumber>20690</PageNumber>
    </MainItem>
  </ItemGroup>
  <ItemGroup>
    <MainItem>
      <Key>Sheppard</Key>
      <Forenames>R</Forenames>
      <PageNumber>1921</PageNumber>
    </MainItem>
  </ItemGroup>
  <ItemGroup>
    <MainItem>
      <Key>Sheppard</Key>
      <Forenames>S. N</Forenames>
      <PageNumber>1091</PageNumber>
    </MainItem>
  </ItemGroup>
  <ItemGroup>
    <MainItem>
      <Key>Sherbahadur</Key>
      <Forenames>Pun</Forenames>
      <PageNumber>3995</PageNumber>
    </MainItem>
  </ItemGroup>
  <ItemGroup>
    <MainItem>
      <Key>Sherman</Key>
      <Forenames>W. H</Forenames>
      <PageNumber>3994</PageNumber>
    </MainItem>
  </ItemGroup>
  <ItemGroup>
    <MainItem>
      <Key>Sherriff</Key>
      <Forenames>J</Forenames>
      <PageNumber>20680</PageNumber>
    </MainItem>
  </ItemGroup>
  <ItemGroup>
    <MainItem>
      <Key>Shieber</Key>
      <Forenames>K. J</Forenames>
      <PageNumber>4000</PageNumber>
    </MainItem>
  </ItemGroup>
  <ItemGroup>
    <MainItem>
      <Key>Shields</Key>
      <Forenames>A. C. G</Forenames>
      <PageNumber>3173</PageNumber>
    </MainItem>
  </ItemGroup>
  <ItemGroup>
    <MainItem>
      <Key>Shields</Key>
      <Forenames>P</Forenames>
      <PageNumber>2748</PageNumber>
    </MainItem>
  </ItemGroup>
  <ItemGroup>
    <MainItem>
      <Key>Shields</Key>
      <Forenames>P. J</Forenames>
      <PageNumber>1918</PageNumber>
    </MainItem>
  </ItemGroup>
  <ItemGroup>
    <MainItem>
      <Key>Shields</Key>
      <Forenames>R</Forenames>
      <PageNumber>4782</PageNumber>
    </MainItem>
  </ItemGroup>
  <ItemGroup>
    <MainItem>
      <Key>Shipp</Key>
      <Text>AM</Text>
      <PageNumber>2321</PageNumber>
    </MainItem>
  </ItemGroup>
  <ItemGroup>
    <MainItem>
      <Key>Shirley</Key>
      <Forenames>G. L</Forenames>
      <PageNumber>20688</PageNumber>
    </MainItem>
  </ItemGroup>
  <ItemGroup>
    <MainItem>
      <Key>Shivakumar</Key>
      <Title>Limbu .</Title>
      <PageNumber>2749</PageNumber>
    </MainItem>
  </ItemGroup>
  <ItemGroup>
    <MainItem>
      <Key>Shooter</Key>
      <Forenames>J</Forenames>
      <PageNumber>2751</PageNumber>
    </MainItem>
  </ItemGroup>
  <ItemGroup>
    <MainItem>
      <Key>Short</Key>
      <Forenames>A. F.</Forenames>
      <PageNumber>4392</PageNumber>
    </MainItem>
  </ItemGroup>
  <ItemGroup>
    <MainItem>
      <Key>Short</Key>
      <Forenames>C. B. H</Forenames>
      <PageNumber>3994</PageNumber>
    </MainItem>
  </ItemGroup>
  <ItemGroup>
    <MainItem>
      <Key>Short</Key>
      <Forenames>D. S</Forenames>
      <PageNumber>20683</PageNumber>
    </MainItem>
  </ItemGroup>
  <ItemGroup>
    <MainItem>
      <Key>Short</Key>
      <Forenames>R. J. K</Forenames>
      <PageNumber>4388</PageNumber>
    </MainItem>
  </ItemGroup>
  <ItemGroup>
    <MainItem>
      <Key>Shuker</Key>
      <Forenames>K. A</Forenames>
      <PageNumber>1091</PageNumber>
    </MainItem>
  </ItemGroup>
  <ItemGroup>
    <MainItem>
      <Key>Sidorowicz</Key>
      <Forenames>S. B</Forenames>
      <PageNumber>3997</PageNumber>
    </MainItem>
  </ItemGroup>
  <ItemGroup>
    <MainItem>
      <Key>Silajit</Key>
      <Forenames>Gurung</Forenames>
      <PageNumber>3995</PageNumber>
    </MainItem>
  </ItemGroup>
  <ItemGroup>
    <MainItem>
      <Key>Silk</Key>
      <Forenames>G. A</Forenames>
      <PageNumber>20680</PageNumber>
    </MainItem>
  </ItemGroup>
  <ItemGroup>
    <MainItem>
      <Key>Sillett</Key>
      <Forenames>T</Forenames>
      <PageNumber>20683</PageNumber>
    </MainItem>
  </ItemGroup>
  <ItemGroup>
    <MainItem>
      <Key>Silverlock</Key>
      <Forenames>D. R</Forenames>
      <PageNumber>3173</PageNumber>
    </MainItem>
  </ItemGroup>
  <ItemGroup>
    <MainItem>
      <Key>Silvester</Key>
      <Forenames>J. L</Forenames>
      <PageNumber>20680</PageNumber>
    </MainItem>
  </ItemGroup>
  <ItemGroup>
    <MainItem>
      <Key>Sim</Key>
      <Forenames>H. D</Forenames>
      <PageNumber>1519</PageNumber>
    </MainItem>
  </ItemGroup>
  <ItemGroup>
    <MainItem>
      <Key>Simm</Key>
      <Forenames>G</Forenames>
      <PageNumber>3997</PageNumber>
    </MainItem>
  </ItemGroup>
  <ItemGroup>
    <MainItem>
      <Key>Simm</Key>
      <Forenames>J. K</Forenames>
      <PageNumber>20686</PageNumber>
    </MainItem>
  </ItemGroup>
  <ItemGroup>
    <MainItem>
      <Key>Sinunonds</Key>
      <Forenames>B. P</Forenames>
      <PageNumber>20689</PageNumber>
    </MainItem>
  </ItemGroup>
  <ItemGroup>
    <MainItem>
      <Key>Simmonds</Key>
      <Forenames>M. J</Forenames>
      <PageNumber>3996</PageNumber>
    </MainItem>
  </ItemGroup>
  <ItemGroup>
    <MainItem>
      <Key>Sinunonds</Key>
      <Forenames>R. C. F.</Forenames>
      <PageNumber>4385</PageNumber>
    </MainItem>
  </ItemGroup>
  <ItemGroup>
    <MainItem>
      <Key>Simmons</Key>
      <Forenames>I. J</Forenames>
      <PageNumber>20689</PageNumber>
    </MainItem>
  </ItemGroup>
  <ItemGroup>
    <MainItem>
      <Key>Simmons</Key>
      <Forenames>S. I.</Forenames>
      <PageNumber>3997</PageNumber>
      <PageNumber>20685</PageNumber>
    </MainItem>
  </ItemGroup>
  <ItemGroup>
    <MainItem>
      <Key>Simms</Key>
      <Forenames>V. A</Forenames>
      <PageNumber>2322</PageNumber>
    </MainItem>
  </ItemGroup>
  <ItemGroup>
    <MainItem>
      <Key>Simpson</Key>
      <Forenames>B. F</Forenames>
      <PageNumber>4387</PageNumber>
    </MainItem>
  </ItemGroup>
  <ItemGroup>
    <MainItem>
      <Key>Simpson</Key>
      <Forenames>C. L</Forenames>
      <PageNumber>1517</PageNumber>
    </MainItem>
  </ItemGroup>
  <ItemGroup>
    <MainItem>
      <Key>Simpson</Key>
      <Forenames>J. B</Forenames>
      <PageNumber>2315</PageNumber>
    </MainItem>
  </ItemGroup>
  <ItemGroup>
    <MainItem>
      <Key>Simpson</Key>
      <Forenames>J. G. M</Forenames>
      <PageNumber>3173</PageNumber>
    </MainItem>
  </ItemGroup>
  <ItemGroup>
    <MainItem>
      <Key>Simpson</Key>
      <Forenames>J. T. F</Forenames>
      <PageNumber>1088</PageNumber>
    </MainItem>
  </ItemGroup>
  <ItemGroup>
    <MainItem>
      <Key>Simpson</Key>
      <Forenames>K</Forenames>
      <PageNumber>3999</PageNumber>
    </MainItem>
  </ItemGroup>
  <ItemGroup>
    <MainItem>
      <Key>Sinclair</Key>
      <Forenames>J. S</Forenames>
      <PageNumber>4782</PageNumber>
    </MainItem>
  </ItemGroup>
  <ItemGroup>
    <MainItem>
      <Key>Sinclair</Key>
      <Forenames>M</Forenames>
      <PageNumber>3993</PageNumber>
    </MainItem>
  </ItemGroup>
  <ItemGroup>
    <MainItem>
      <Key>Sinclair</Key>
      <Forenames>M. A</Forenames>
      <PageNumber>2754</PageNumber>
    </MainItem>
  </ItemGroup>
  <ItemGroup>
    <MainItem>
      <Key>Sinclair</Key>
      <Forenames>W. G</Forenames>
      <PageNumber>1091</PageNumber>
    </MainItem>
  </ItemGroup>
  <ItemGroup>
    <MainItem>
      <Key>Sington</Key>
      <Forenames>D. K</Forenames>
      <PageNumber>2320</PageNumber>
    </MainItem>
  </ItemGroup>
  <ItemGroup>
    <MainItem>
      <Key>Sinton</Key>
      <Forenames>J. R</Forenames>
      <PageNumber>4001</PageNumber>
    </MainItem>
  </ItemGroup>
  <ItemGroup>
    <MainItem>
      <Key>Sked</Key>
      <Forenames>R. F</Forenames>
      <PageNumber>4784</PageNumber>
    </MainItem>
  </ItemGroup>
  <ItemGroup>
    <MainItem>
      <Key>Skelding</Key>
      <Forenames>D</Forenames>
      <PageNumber>1090</PageNumber>
    </MainItem>
  </ItemGroup>
  <ItemGroup>
    <MainItem>
      <Key>Skinner</Key>
      <Forenames>M. G</Forenames>
      <PageNumber>1522</PageNumber>
    </MainItem>
  </ItemGroup>
  <ItemGroup>
    <MainItem>
      <Key>Skinner</Key>
      <Forenames>P. E</Forenames>
      <PageNumber>4001</PageNumber>
    </MainItem>
  </ItemGroup>
  <ItemGroup>
    <MainItem>
      <Key>Skinner</Key>
      <Forenames>P. W</Forenames>
      <PageNumber>20679</PageNumber>
    </MainItem>
  </ItemGroup>
  <ItemGroup>
    <MainItem>
      <Key>Skoyles</Key>
      <Forenames>K. J</Forenames>
      <PageNumber>20688</PageNumber>
    </MainItem>
  </ItemGroup>
  <ItemGroup>
    <MainItem>
      <Key>Sladden</Key>
      <Text>CP</Text>
      <PageNumber>710</PageNumber>
    </MainItem>
  </ItemGroup>
  <ItemGroup>
    <MainItem>
      <Key>Slaney</Key>
      <Forenames>P. J</Forenames>
      <PageNumber>3181</PageNumber>
    </MainItem>
  </ItemGroup>
  <ItemGroup>
    <MainItem>
      <Key>Slater</Key>
      <Forenames>C. R</Forenames>
      <PageNumber>3172</PageNumber>
    </MainItem>
  </ItemGroup>
  <ItemGroup>
    <MainItem>
      <Key>Slater</Key>
      <Forenames>N. J</Forenames>
      <PageNumber>20689</PageNumber>
    </MainItem>
  </ItemGroup>
  <ItemGroup>
    <MainItem>
      <Key>Slatter</Key>
      <Forenames>F. G</Forenames>
      <PageNumber>3180</PageNumber>
    </MainItem>
  </ItemGroup>
  <ItemGroup>
    <MainItem>
      <Key>Slattery</Key>
      <Forenames>M. L</Forenames>
      <PageNumber>2320</PageNumber>
    </MainItem>
  </ItemGroup>
  <ItemGroup>
    <MainItem>
      <Key>Sleigh</Key>
      <Forenames>D. J</Forenames>
      <PageNumber>710</PageNumber>
    </MainItem>
  </ItemGroup>
  <ItemGroup>
    <MainItem>
      <Key>Slinger</Key>
      <Forenames>A. P</Forenames>
      <PageNumber>4392</PageNumber>
    </MainItem>
  </ItemGroup>
  <ItemGroup>
    <MainItem>
      <Key>Sloan</Key>
      <Forenames>A. G</Forenames>
      <PageNumber>1516</PageNumber>
    </MainItem>
  </ItemGroup>
  <ItemGroup>
    <MainItem>
      <Key>Sloan</Key>
      <Forenames>R. A</Forenames>
      <PageNumber>1920</PageNumber>
    </MainItem>
  </ItemGroup>
  <ItemGroup>
    <MainItem>
      <Key>Slocombe</Key>
      <Forenames>P. H</Forenames>
      <PageNumber>3999</PageNumber>
    </MainItem>
  </ItemGroup>
  <ItemGroup>
    <MainItem>
      <Key>Smailes</Key>
      <Forenames>C.C.R</Forenames>
      <PageNumber>1918</PageNumber>
    </MainItem>
  </ItemGroup>
  <ItemGroup>
    <MainItem>
      <Key>Small</Key>
      <Forenames>D. J. R</Forenames>
      <PageNumber>1087</PageNumber>
    </MainItem>
  </ItemGroup>
  <ItemGroup>
    <MainItem>
      <Key>Small</Key>
      <Forenames>M. C</Forenames>
      <PageNumber>1521</PageNumber>
    </MainItem>
  </ItemGroup>
  <ItemGroup>
    <MainItem>
      <Key>Smalley</Key>
      <Forenames>D. J</Forenames>
      <PageNumber>1518</PageNumber>
    </MainItem>
  </ItemGroup>
  <ItemGroup>
    <MainItem>
      <Key>Smart</Key>
      <Forenames>J. G</Forenames>
      <PageNumber>1922</PageNumber>
    </MainItem>
  </ItemGroup>
  <ItemGroup>
    <MainItem>
      <Key>Smit</Key>
      <Forenames>S. B</Forenames>
      <PageNumber>4384</PageNumber>
    </MainItem>
  </ItemGroup>
  <ItemGroup>
    <MainItem>
      <Key>Smith</Key>
      <Forenames>A</Forenames>
      <PageNumber>1522</PageNumber>
      <PageNumber>1523</PageNumber>
    </MainItem>
  </ItemGroup>
  <ItemGroup>
    <MainItem>
      <Key>Smith</Key>
      <Forenames>A. B</Forenames>
      <PageNumber>1917</PageNumber>
    </MainItem>
  </ItemGroup>
  <ItemGroup>
    <MainItem>
      <Key>Smith</Key>
      <Forenames>A. D</Forenames>
      <PageNumber>1092</PageNumber>
    </MainItem>
  </ItemGroup>
  <ItemGroup>
    <MainItem>
      <Key>Smith</Key>
      <Forenames>A. E</Forenames>
      <PageNumber>3993</PageNumber>
    </MainItem>
  </ItemGroup>
  <ItemGroup>
    <MainItem>
      <Key>Smith</Key>
      <Forenames>A. J</Forenames>
      <PageNumber>2322</PageNumber>
    </MainItem>
  </ItemGroup>
  <ItemGroup>
    <MainItem>
      <Key>Smith</Key>
      <Forenames>A. L</Forenames>
      <PageNumber>1095</PageNumber>
      <PageNumber>4783</PageNumber>
    </MainItem>
  </ItemGroup>
  <ItemGroup>
    <MainItem>
      <Key>Smith</Key>
      <Forenames>A. M.</Forenames>
      <PageNumber>2319</PageNumber>
      <PageNumber>4784</PageNumber>
    </MainItem>
  </ItemGroup>
  <ItemGroup>
    <MainItem>
      <Key>Smith</Key>
      <Forenames>B</Forenames>
      <PageNumber>710</PageNumber>
    </MainItem>
  </ItemGroup>
  <ItemGroup>
    <MainItem>
      <Key>Smith</Key>
      <Forenames>B. C</Forenames>
      <PageNumber>3999</PageNumber>
      <PageNumber>4001</PageNumber>
    </MainItem>
  </ItemGroup>
  <ItemGroup>
    <MainItem>
      <Key>Smith</Key>
      <Forenames>B. M</Forenames>
      <PageNumber>1519</PageNumber>
    </MainItem>
  </ItemGroup>
  <ItemGroup>
    <MainItem>
      <Key>Smith</Key>
      <Forenames>B. R</Forenames>
      <PageNumber>1091</PageNumber>
    </MainItem>
  </ItemGroup>
  <ItemGroup>
    <MainItem>
      <Key>Smith</Key>
      <Forenames>C. F</Forenames>
      <PageNumber>3999</PageNumber>
    </MainItem>
  </ItemGroup>
  <ItemGroup>
    <MainItem>
      <Key>Smith</Key>
      <Forenames>D</Forenames>
      <PageNumber>20684</PageNumber>
    </MainItem>
  </ItemGroup>
  <ItemGroup>
    <MainItem>
      <Key>Smith</Key>
      <Forenames>D. J. D</Forenames>
      <PageNumber>2750</PageNumber>
    </MainItem>
  </ItemGroup>
  <ItemGroup>
    <MainItem>
      <Key>Smith</Key>
      <Forenames>D. M. R</Forenames>
      <PageNumber>3175</PageNumber>
    </MainItem>
  </ItemGroup>
  <ItemGroup>
    <MainItem>
      <Key>Smith</Key>
      <Forenames>E. J. D</Forenames>
      <PageNumber>1920</PageNumber>
    </MainItem>
  </ItemGroup>
  <ItemGroup>
    <MainItem>
      <Key>Smith</Key>
      <Forenames>F. G</Forenames>
      <PageNumber>1524</PageNumber>
    </MainItem>
  </ItemGroup>
  <ItemGroup>
    <MainItem>
      <Key>Smith</Key>
      <Forenames>F. P</Forenames>
      <PageNumber>20690</PageNumber>
    </MainItem>
  </ItemGroup>
  <ItemGroup>
    <MainItem>
      <Key>Smith</Key>
      <Forenames>G</Forenames>
      <PageNumber>3174</PageNumber>
    </MainItem>
  </ItemGroup>
  <ItemGroup>
    <MainItem>
      <Key>Smith</Key>
      <Forenames>G. E</Forenames>
      <PageNumber>1089</PageNumber>
    </MainItem>
  </ItemGroup>
  <ItemGroup>
    <MainItem>
      <Key>Smith</Key>
      <Forenames>G. F. W</Forenames>
      <PageNumber>3172</PageNumber>
    </MainItem>
  </ItemGroup>
  <ItemGroup>
    <MainItem>
      <Key>Smith</Key>
      <Forenames>G. J</Forenames>
      <PageNumber>3177</PageNumber>
    </MainItem>
  </ItemGroup>
  <ItemGroup>
    <MainItem>
      <Key>Smith</Key>
      <Forenames>G. N</Forenames>
      <PageNumber>4783</PageNumber>
    </MainItem>
  </ItemGroup>
  <ItemGroup>
    <MainItem>
      <Key>Smith</Key>
      <Forenames>G. R. G</Forenames>
      <PageNumber>3181</PageNumber>
    </MainItem>
  </ItemGroup>
  <ItemGroup>
    <MainItem>
      <Key>Smith</Key>
      <Forenames>H. A</Forenames>
      <PageNumber>338</PageNumber>
    </MainItem>
  </ItemGroup>
  <ItemGroup>
    <MainItem>
      <Key>Smith</Key>
      <Forenames>H. B</Forenames>
      <PageNumber>1524</PageNumber>
    </MainItem>
  </ItemGroup>
  <ItemGroup>
    <MainItem>
      <Key>Smith</Key>
      <Forenames>J. A</Forenames>
      <PageNumber>2320</PageNumber>
    </MainItem>
  </ItemGroup>
  <ItemGroup>
    <MainItem>
      <Key>Smith</Key>
      <Forenames>J. C. A</Forenames>
      <PageNumber>20680</PageNumber>
    </MainItem>
  </ItemGroup>
  <KeyDitto>___ ___ ___ ___ ___ ___ ___ ___ ___ ___ ___ ___ ___ ___ ___</KeyDitto>
</Index>

